[
  {
    "month": "January",
    "date": "Jan 1",
    "location": "Throughout Chennai",
    "eventName": "Chennai Dance & Music Festival"
  },
  {
    "month": "January",
    "date": "Jan 6",
    "location": "Sabarmati Riverfront, Ashram Road, Ahmedabad, Gujarat",
    "eventName": "International Kite Festival"
  },
  {
    "month": "January",
    "date": "Jan 10",
    "location": "Mylapore, Chennai, Tamil Nadu",
    "eventName": "Pongol & the Mylapore Festival"
  },
  {
    "month": "January",
    "date": "Jan 14",
    "location": "Jawaharlal Nehru Stadium, Gate 14, Bhishma Pitamah Road, Pragati  Vihar, Lodi Colony, Delhi",
    "eventName": "National Street Food Festival"
  },
  {
    "month": "January",
    "date": "Jan 14",
    "location": "Joydev Kenduli village, around 30 kilometers from Shantiniketan in the  Birbhum district of West Bengal",
    "eventName": "Kenduli Mela"
  },
  {
    "month": "January",
    "date": "Jan 18",
    "location": "Mumbai",
    "eventName": "Kabir Festival"
  },
  {
    "month": "January",
    "date": "Jan 18",
    "location": "Rajarani Temple, Bhubaneswar, Odisha",
    "eventName": "Rajarani Music Festival"
  },
  {
    "month": "January",
    "date": "Jan 24",
    "location": "Diggi Palace, Jaipur, Rajasthan",
    "eventName": "Jaipur Literature Festival"
  },
  {
    "month": "January",
    "date": "Jan 25",
    "location": "Ernakulam, Kochi, Kerala",
    "eventName": "Ernakulathappan Uthsavam"
  },
  {
    "month": "January",
    "date": "Jan 29",
    "location": "Ludhiana, Punjab",
    "eventName": "Kila Raipur Sports Festival"
  },
  {
    "month": "January",
    "date": "Jan 31",
    "location": "NSIC Exhibition Grounds (Okhla), New Delhi",
    "eventName": "India Art Fair"
  },
  {
    "month": "February",
    "date": "Feb 1",
    "location": "Surajkund, in the Faridabad district a short distance from South Delhi",
    "eventName": "Surajkund International Crafts Mela"
  },
  {
    "month": "February",
    "date": "Feb 1",
    "location": "Mohor Kunja in Kolkata",
    "eventName": "Sur Jahan World Peace Music Festival"
  },
  {
    "month": "February",
    "date": "Feb 2",
    "location": "Mumbai",
    "eventName": "Kala Ghoda Arts Festival"
  },
  {
    "month": "February",
    "date": "Feb 10",
    "location": "Goa",
    "eventName": "Goa Carnival"
  },
  {
    "month": "February",
    "date": "Feb 12",
    "location": "Nawalgarh, Rajasthan",
    "eventName": "Shekhawati Heritage Festival"
  },
  {
    "month": "February",
    "date": "Feb 18",
    "location": "Agra, Uttar Pradesh",
    "eventName": "Taj Mahotsav"
  },
  {
    "month": "February",
    "date": "Feb 19",
    "location": "Pariyanampetta Bhagavathy Temple, Kattukulam, Palakkad district of Kerala",
    "eventName": "Pariyanampetta Pooram"
  },
  {
    "month": "February",
    "date": "Feb 20",
    "location": "Trivandrum (Thiruvananthapuram), Kerala",
    "eventName": "Attukal Pongola"
  },
  {
    "month": "February",
    "date": "Feb 20",
    "location": "Khajuraho, Madhya Pradesh",
    "eventName": "Khajuraho Dance Festival"
  },
  {
    "month": "February",
    "date": "Feb 22",
    "location": "Kuttikkol Thampuratty Bhagavathy Temple at Kuttikkol, Kasaragod district  of Kerala",
    "eventName": "Kuttikkol Thampuratty Theyyam"
  },
  {
    "month": "March",
    "date": "Mar 1",
    "location": "Parmarth Niketan, Rishikesh",
    "eventName": "International Yoga Festival"
  },
  {
    "month": "March",
    "date": "Mar 1",
    "location": "Aizawl, the capital of Mizoram in northeast India.",
    "eventName": "Chapchar Kut"
  },
  {
    "month": "March",
    "date": "Mar 4",
    "location": "Kollam, Kerala",
    "eventName": "Paripally Gajamela"
  },
  {
    "month": "March",
    "date": "Mar 10",
    "location": "Velas village, Ratnagiri, Maharashtra",
    "eventName": "Konkan Velas Turtle Festival"
  },
  {
    "month": "March",
    "date": "Mar 14",
    "location": "Sree Padmanabha Swamy Temple, Trivandrum, Kerala",
    "eventName": "Painkuni Festival"
  },
  {
    "month": "March",
    "date": "Mar 15",
    "location": "Ziro, Arunachal Pradesh",
    "eventName": "Myoko"
  },
  {
    "month": "March",
    "date": "Mar 17",
    "location": "Elankavu Sree Bhagavathy Temple, Vadayar, Kottayam District, Kerala",
    "eventName": "Attuvela Mahotsavam"
  },
  {
    "month": "March",
    "date": "Mar 21",
    "location": "Udaipur",
    "eventName": "Holi – Mewar Holika Dahan"
  },
  {
    "month": "March",
    "date": "Mar 21",
    "location": "Throughout Goa",
    "eventName": "Shigmo"
  },
  {
    "month": "March",
    "date": "Mar 21",
    "location": "All over Rajasthan, Jaipur has a notable celebration",
    "eventName": "Gangaur Festival"
  },
  {
    "month": "March",
    "date": "Mar 24",
    "location": "Thirunakkara Mahadeva Temple, Kottayam district, Kerala",
    "eventName": "Thirunakkara Arattu"
  },
  {
    "month": "April",
    "date": "Apr 1",
    "location": "Kashmir; Indira Gandhi Memorial Tulip Garden, Srinagar, Kashmir",
    "eventName": "Tulip Festival"
  },
  {
    "month": "April",
    "date": "Apr 1",
    "location": "Mon district of Nagaland in North East India",
    "eventName": "The Aoling Festival"
  },
  {
    "month": "April",
    "date": "Apr 6",
    "location": "Mumbai, Maharashtra",
    "eventName": "Gudi Padwa Shoba Yatra (Traditional new year for Marathi Hindus)"
  },
  {
    "month": "April",
    "date": "Apr 6",
    "location": "Udaipur",
    "eventName": "Mewar Festival"
  },
  {
    "month": "April",
    "date": "Apr 10",
    "location": "Meenakshi Temple, Madurai, Tamil Nadu",
    "eventName": "Chithirai Festival"
  },
  {
    "month": "April",
    "date": "Apr 13",
    "location": "Religious celebrations and processions take place at Ayodhya in Uttar Pradesh",
    "eventName": "Ram Navami"
  },
  {
    "month": "April",
    "date": "Apr 14",
    "location": "Amritsar, Punjab",
    "eventName": "Baisakhi"
  },
  {
    "month": "April",
    "date": "Apr 19",
    "location": "Sankat Mochan Hanuman Temple in Varanasi",
    "eventName": "Sankat Mochan Music Festival"
  },
  {
    "month": "April",
    "date": "Apr 29",
    "location": "Mt. Abu, Rajasthan",
    "eventName": "Mount Abu Summer Festival"
  },
  {
    "month": "May",
    "date": "May 1",
    "location": "Gangtok, Sikkim",
    "eventName": "International Flower Festival"
  },
  {
    "month": "May",
    "date": "May 1",
    "location": "Mokokchung district villages, Nagaland",
    "eventName": "Moatsü Festival"
  },
  {
    "month": "May",
    "date": "May 1",
    "location": "Ooty, Tamil Nadu",
    "eventName": "Ooty Summer Festival"
  },
  {
    "month": "May",
    "date": "May 1",
    "location": "Kedarnath, Badrinath,  Gangotri,  Yamunotri (Uttarakhand)",
    "eventName": "Char Dham Yatra"
  },
  {
    "month": "May",
    "date": "May 5",
    "location": "Delhi",
    "eventName": "Ramadan"
  },
  {
    "month": "May",
    "date": "May 8",
    "location": "Indira Gandhi National Centre for the Arts, New Delhi",
    "eventName": "Festival of Bharat"
  },
  {
    "month": "May",
    "date": "May 10",
    "location": "Pragati Maidan, New Delhi",
    "eventName": "The Yogshala Expo"
  },
  {
    "month": "May",
    "date": "May 14",
    "location": "Manali, Himachal Pradesh",
    "eventName": "Dhungri Mela"
  },
  {
    "month": "May",
    "date": "May 18",
    "location": "Mahabodhi Temple, Bodhgaya, Bihar",
    "eventName": "Buddha Jayanti"
  },
  {
    "month": "May",
    "date": "May 18",
    "location": "Gangtok, Sikkim",
    "eventName": "Saga Dawa Düchen"
  },
  {
    "month": "May",
    "date": "May 26",
    "location": "Kannur, Kerala",
    "eventName": "Kottiyoor Utsavam"
  },
  {
    "month": "June",
    "date": "Jun 1",
    "location": "Lucknow, Uttar Pradesh",
    "eventName": "Uttar Pradesh Mango Festival"
  },
  {
    "month": "June",
    "date": "Jun 2",
    "location": "Shimla, Himachal Pradesh",
    "eventName": "Shimla Summer Festival"
  },
  {
    "month": "June",
    "date": "Jun 9",
    "location": "Sambalpur district, Orissa",
    "eventName": "Sital Sasthi"
  },
  {
    "month": "June",
    "date": "Jun 12",
    "location": "Haridwar, Uttarakhand",
    "eventName": "Ganga Dussehra"
  },
  {
    "month": "June",
    "date": "Jun 16",
    "location": "Ochira Parabrahma Temple, Kollam, Kerala",
    "eventName": "Ochira Kali"
  },
  {
    "month": "June",
    "date": "Jun 22",
    "location": "Kamakhya Temple, Guwahati, Assam",
    "eventName": "Ambubachi Mela"
  },
  {
    "month": "June",
    "date": "Jun 24",
    "location": "Throughout Goa",
    "eventName": "Sao Joao Festival"
  },
  {
    "month": "July",
    "date": "Jul 1",
    "location": "Lamayuru Monastery, Ladakh, Jammu and Kashmir",
    "eventName": "Yuru Kabgyat"
  },
  {
    "month": "July",
    "date": "Jul 1",
    "location": "Dilli Haat market in Janakpuri, New Delhi",
    "eventName": "International Mango Festival"
  },
  {
    "month": "July",
    "date": "Jul 1",
    "location": "Nishagandhi Auditorium, Kanakakunnu Palace Grounds, Trivandrum,  Kerala",
    "eventName": "Nishagandhi Monsoon Music Festival"
  },
  {
    "month": "July",
    "date": "Jul 4",
    "location": "Jagannath Temple, Puri, Odisha",
    "eventName": "Rath Yatra"
  },
  {
    "month": "July",
    "date": "Jul 4",
    "location": "Ziro, Arunachal Pradesh",
    "eventName": "Dree Festival"
  },
  {
    "month": "July",
    "date": "Jul 4",
    "location": "QSecunderabad,  Hyderabad ( Telangana)",
    "eventName": "Bonalu (Ashada Jatra Utsavalu)"
  },
  {
    "month": "July",
    "date": "Jul 11",
    "location": "Hemis Monastery, Leh, Ladakh",
    "eventName": "Hemis Festival"
  },
  {
    "month": "July",
    "date": "Jul 15",
    "location": "Pampa River at Champakulam village, near Alleppey, Kerala",
    "eventName": "Champakulam Boat Race"
  },
  {
    "month": "July",
    "date": "Jul 15",
    "location": "Jowai, Jaintia Hills, Meghalaya",
    "eventName": "Behdienkhlam"
  },
  {
    "month": "July",
    "date": "Jul 15",
    "location": "New Delhi to Leh",
    "eventName": "Royal Enfield Himalayan Odyssey"
  },
  {
    "month": "July",
    "date": "Jul 16",
    "location": "Mathura, Uttar Pradesh",
    "eventName": "Guru Purnima"
  },
  {
    "month": "July",
    "date": "Jul 30",
    "location": "Karsha Monastery, Zanskar region, Jammu and Kashmir",
    "eventName": "Karsha Gustor Festival"
  },
  {
    "month": "August",
    "date": "Aug 1",
    "location": "Yumthang Valley, Sikkim",
    "eventName": "Drupka Teshi Festival"
  },
  {
    "month": "August",
    "date": "Aug 1",
    "location": "Kovalam village, Tamil Nadu",
    "eventName": "Covelong Point Surf, Music and Yoga Festival"
  },
  {
    "month": "August",
    "date": "Aug 3",
    "location": "Jaipur,  Bundi ( Rajasthan )",
    "eventName": "Teej"
  },
  {
    "month": "August",
    "date": "Aug 10",
    "location": "Alleppey, Kerala",
    "eventName": "Nehru Trophy Boat Race"
  },
  {
    "month": "August",
    "date": "Aug 15",
    "location": "Red Fort, Delhi",
    "eventName": "Independence Day"
  },
  {
    "month": "August",
    "date": "Aug 17",
    "location": "Mumbai, Maharashtra",
    "eventName": "Parsi New Year"
  },
  {
    "month": "August",
    "date": "Aug 18",
    "location": "Chennai, Tamil Nadu",
    "eventName": "Madras Week"
  },
  {
    "month": "August",
    "date": "Aug 22",
    "location": "Bishnupur, Bankura district, West Bengal",
    "eventName": "Jhapan Mela"
  },
  {
    "month": "August",
    "date": "Aug 23",
    "location": "Tarnetar, near the town of Thangadh, Gujarat",
    "eventName": "Tarnetar Fair"
  },
  {
    "month": "August",
    "date": "Aug 24",
    "location": "Divar Island, near Panjim, Goa",
    "eventName": "Bonderam Festival"
  },
  {
    "month": "August",
    "date": "Aug 24",
    "location": "Vrindavan, Uttar Pradesh",
    "eventName": "Janmashtami"
  },
  {
    "month": "August",
    "date": "Aug 25",
    "location": "Gogamedi village, Hanumangarh district, Rajasthan",
    "eventName": "Gogamedi Fair"
  },
  {
    "month": "September",
    "date": "Sep 1",
    "location": "Tripunithura, Kochi, Kerala",
    "eventName": "Athachamayam"
  },
  {
    "month": "September",
    "date": "Sep 1",
    "location": "Kochi, Kerala",
    "eventName": "Onam Festival"
  },
  {
    "month": "September",
    "date": "Sep 2",
    "location": "Mumbai, Maharashtra",
    "eventName": "Ganesh Festival"
  },
  {
    "month": "September",
    "date": "Sep 2",
    "location": "Raigarh, Chhattisgarh",
    "eventName": "Chakradhar Samaroh"
  },
  {
    "month": "September",
    "date": "Sep 4",
    "location": "City Palace, Jaipur, Rajasthan",
    "eventName": "The Monsoon Festival"
  },
  {
    "month": "September",
    "date": "Sep 4",
    "location": "Swaraj Round in Thrissur, Kerala",
    "eventName": "Onam Pulikali"
  },
  {
    "month": "September",
    "date": "Sep 10",
    "location": "Udaipur, Rajasthan",
    "eventName": "Muharram Festival and Tazia Procession"
  },
  {
    "month": "September",
    "date": "Sep 12",
    "location": "Ramnagar, Varanasi district, Uttar Pradesh",
    "eventName": "Ramlila"
  },
  {
    "month": "September",
    "date": "Sep 25",
    "location": "Leh, Ladakh, Jammu and Kashmir",
    "eventName": "Ladakh Festival"
  },
  {
    "month": "September",
    "date": "Sep 27",
    "location": "Ziro Valley, Arunachal Pradesh",
    "eventName": "Ziro Festival of Music"
  },
  {
    "month": "September",
    "date": "Sep 28",
    "location": "Pune, Maharashtra",
    "eventName": "Pune International Literary Festival"
  },
  {
    "month": "September",
    "date": "Sep 29",
    "location": "Hyderabad, Telangana",
    "eventName": "Bathukamma"
  },
  {
    "month": "October",
    "date": "Oct 2",
    "location": "Raj Ghat, New Delhi",
    "eventName": "Gandhi’s Birthday"
  },
  {
    "month": "October",
    "date": "Oct 2",
    "location": "Jodhpur,  Jaisalmer,  Bikaner (Rajasthan)",
    "eventName": "Kabir Yatra"
  },
  {
    "month": "October",
    "date": "Oct 4",
    "location": "Kolkata, West Bengal",
    "eventName": "Durga Puja"
  },
  {
    "month": "October",
    "date": "Oct 10",
    "location": "Abhaneri village, Bandikui Dausa district, Rajasthan",
    "eventName": "Abhaneri Festival"
  },
  {
    "month": "October",
    "date": "Oct 10",
    "location": "Mehrangarh Fort, Jodhpur, Rajasthan",
    "eventName": "Rajasthan International Folk Festival"
  },
  {
    "month": "October",
    "date": "Oct 10",
    "location": "Jodhpur, Rajasthan",
    "eventName": "Marwar Festival"
  },
  {
    "month": "October",
    "date": "Oct 12",
    "location": "Pushkar, Rajasthan",
    "eventName": "The Sacred Pushkar"
  },
  {
    "month": "October",
    "date": "Oct 17",
    "location": "City Palace, Udaipur, Rajasthan",
    "eventName": "World Living Heritage Festival"
  },
  {
    "month": "October",
    "date": "Oct 26",
    "location": "Tawang, Arunachal Pradesh",
    "eventName": "Tawang Festival"
  },
  {
    "month": "October",
    "date": "Oct 27",
    "location": "Golden Temple, Amritsar, Punjab",
    "eventName": "Diwali"
  },
  {
    "month": "November",
    "date": "Nov 1",
    "location": "Rishikesh, Uttarakhand",
    "eventName": "International Yoga & Music Festival"
  },
  {
    "month": "November",
    "date": "Nov 1",
    "location": "Great Rann of Kutch salt desert, Dhordo, Gujarat",
    "eventName": "Rann Utsav"
  },
  {
    "month": "November",
    "date": "Nov 2",
    "location": "Assi Ghat, Varanasi, Uttar Pradesh",
    "eventName": "Chhath Puja"
  },
  {
    "month": "November",
    "date": "Nov 3",
    "location": "Hampi, Karnataka",
    "eventName": "Hampi Utsav"
  },
  {
    "month": "November",
    "date": "Nov 4",
    "location": "Pushkar, Rajasthan",
    "eventName": "Pushkar Camel Fair"
  },
  {
    "month": "November",
    "date": "Nov 8",
    "location": "Garo Hills, Meghalaya",
    "eventName": "Wangala Festival"
  },
  {
    "month": "November",
    "date": "Nov 9",
    "location": "Srinagar, Kashmir",
    "eventName": "The Prophet Mohammed’s Birthday"
  },
  {
    "month": "November",
    "date": "Nov 12",
    "location": "Amritsar, Punjab",
    "eventName": "Guru Nanak Jayanti"
  },
  {
    "month": "November",
    "date": "Nov 12",
    "location": "Varanasi, Uttar Pradesh",
    "eventName": "Ganga Mahotsav and Dev Deepawali"
  },
  {
    "month": "November",
    "date": "Nov 15",
    "location": "Bundi, Rajasthan",
    "eventName": "Bundi Utsav"
  },
  {
    "month": "November",
    "date": "Nov 22",
    "location": "Gohar Mahal, Bhopal, Madhya Pradesh",
    "eventName": "Potters Market"
  },
  {
    "month": "December",
    "date": "Dec 1",
    "location": "Kumbhalgarh, Rajasthan",
    "eventName": "Kumbhalgarh Festival"
  },
  {
    "month": "December",
    "date": "Dec 1",
    "location": "New Delhi",
    "eventName": "Delhi International Arts Festival"
  },
  {
    "month": "December",
    "date": "Dec 1",
    "location": "Konark Sun Temple, Puri, Odisha",
    "eventName": "Konark Festival"
  },
  {
    "month": "December",
    "date": "Dec 1",
    "location": "Kisama Heritage Village, Nagaland",
    "eventName": "Hornbill Festival"
  },
  {
    "month": "December",
    "date": "Dec 2",
    "location": "JVPD Ground, Juhu, Mumbai, Maharashtra",
    "eventName": "One Earth Festival"
  },
  {
    "month": "December",
    "date": "Dec 14",
    "location": "Alsisar Mahal, Shekhawati region, Rajasthan",
    "eventName": "Magnetic Fields Festival"
  },
  {
    "month": "December",
    "date": "Dec 15",
    "location": "Panaji, Goa",
    "eventName": "Serendipity Arts Festival"
  },
  {
    "month": "December",
    "date": "Dec 21",
    "location": "Udaipur, Rajasthan",
    "eventName": "Shilpgram Art and Craft Fair"
  },
  {
    "month": "December",
    "date": "Dec 22",
    "location": "Bamnia village, Purulia, West Bengal",
    "eventName": "Chhau Jhumur Utsav"
  },
  {
    "month": "December",
    "date": "Dec 24",
    "location": "Shantiniketan, West Bengal",
    "eventName": "Poush Mela"
  },
  {
    "month": "December",
    "date": "Dec 25",
    "location": "Basilica of Bom Jesus, Old Goa, Goa",
    "eventName": "Christmas Day"
  }
]